reflex_wrapper/__init__.py
reflex_wrapper/rx_wrapper.py
reflex_wrapper-0.0.4.dist-info/LICENSE
reflex_wrapper-0.0.4.dist-info/METADATA
reflex_wrapper-0.0.4.dist-info/WHEEL
reflex_wrapper-0.0.4.dist-info/top_level.txt
reflex_wrapper-0.0.4.dist-info/RECORD
