Metadata-Version: 2.1
Name: reflex_wrapper
Version: 0.0.4
Summary: A custom wrapper on top of the reflex library to ease creating and interacting with custom components.
Home-page: https://github.com/B4PT0R/reflex_wrapper
Author: Baptiste Ferrand
Author-email: bferrand.maths@gmail.com
Classifier: Programming Language :: Python :: 3
Classifier: License :: OSI Approved :: MIT License
Classifier: Operating System :: OS Independent
Requires-Python: >=3.6
License-File: LICENSE
Requires-Dist: reflex >=0.4.8
